visiomatic-3.0.6.dist-info/METADATA
visiomatic-3.0.6.dist-info/WHEEL
visiomatic-3.0.6.dist-info/entry_points.txt
visiomatic-3.0.6.dist-info/licenses/LICENSE
visiomatic/__init__.py
visiomatic/client/css/spectrum.css
visiomatic/client/css/themes.css
visiomatic/client/css/visiomatic.css
visiomatic/client/dist/visiomatic.js
visiomatic/client/images/activity.svg
visiomatic/client/images/cds.png
visiomatic/client/images/cfht-logo.svg
visiomatic/client/images/directory.png
visiomatic/client/images/file.png
visiomatic/client/images/folder_open.png
visiomatic/client/images/icon-backward.svg
visiomatic/client/images/icon-backward2.svg
visiomatic/client/images/icon-camera.svg
visiomatic/client/images/icon-clipboard.svg
visiomatic/client/images/icon-cog.svg
visiomatic/client/images/icon-cold.svg
visiomatic/client/images/icon-contrast.svg
visiomatic/client/images/icon-equalizer2.svg
visiomatic/client/images/icon-first.svg
visiomatic/client/images/icon-fullscreen.svg
visiomatic/client/images/icon-grey.svg
visiomatic/client/images/icon-home.svg
visiomatic/client/images/icon-hot.svg
visiomatic/client/images/icon-image.svg
visiomatic/client/images/icon-info.svg
visiomatic/client/images/icon-jet.svg
visiomatic/client/images/icon-last.svg
visiomatic/client/images/icon-left.svg
visiomatic/client/images/icon-location.svg
visiomatic/client/images/icon-magicwand.svg
visiomatic/client/images/icon-magnifyminus.svg
visiomatic/client/images/icon-magnifyplus.svg
visiomatic/client/images/icon-make-group.svg
visiomatic/client/images/icon-map.svg
visiomatic/client/images/icon-menu.svg
visiomatic/client/images/icon-minus.svg
visiomatic/client/images/icon-next.svg
visiomatic/client/images/icon-palette.svg
visiomatic/client/images/icon-pause.svg
visiomatic/client/images/icon-pdf.svg
visiomatic/client/images/icon-play.svg
visiomatic/client/images/icon-plot.svg
visiomatic/client/images/icon-plus.svg
visiomatic/client/images/icon-previous.svg
visiomatic/client/images/icon-print.svg
visiomatic/client/images/icon-reset.svg
visiomatic/client/images/icon-reverse.svg
visiomatic/client/images/icon-right.svg
visiomatic/client/images/icon-settings.svg
visiomatic-3.0.6.dist-info/RECORD
