Metadata-Version: 2.1
Name: VisiOmatic
Version: 3.0.6
Summary: A web application for visualizing astronomical images
Keywords: astronomy,CFHT,imaging
Author-Email: Emmanuel Bertin <bertin@cfht.hawaii.edu>
License: MIT License
Classifier: Programming Language :: Python :: 3
Classifier: Programming Language :: Python :: 3.10
Classifier: Programming Language :: Python :: 3.11
Classifier: Programming Language :: Python :: 3.12
Classifier: Programming Language :: Python :: 3.13
Project-URL: Repository, https://github.com/astromatic/visiomatic
Project-URL: Homepage, https://visiomatic.org
Project-URL: Documentation, https://astromatic.github.io/visiomatic
Requires-Python: >=3.10
Requires-Dist: astropy>=5.0
Requires-Dist: atomics>=1.0
Requires-Dist: fastapi>=0.74
Requires-Dist: jinja2>=3.1.2
Requires-Dist: joblib>=1.0
Requires-Dist: methodtools>=0.4.7
Requires-Dist: numpy>=1.19
Requires-Dist: opencv-python>=4.5
Requires-Dist: orjson>=3.9.0
Requires-Dist: platformdirs>=3.4.0
Requires-Dist: posix_ipc>=1.1.0; platform_system == "Linux"
Requires-Dist: pydantic>=2.2
Requires-Dist: pydantic-settings>=2.2
Requires-Dist: scikit-image>=0.22.0
Requires-Dist: setuptools
Requires-Dist: simplejpeg>=1.6
Requires-Dist: tiler>=0.5
Requires-Dist: ultradict>=0.0.6; platform_system == "Linux"
Requires-Dist: uvicorn[standard]>=0.30
Provides-Extra: test
Requires-Dist: httpx; extra == "test"
Requires-Dist: mypy; extra == "test"
Requires-Dist: pytest-cov; extra == "test"
Provides-Extra: doc
Requires-Dist: autodoc_pydantic>=2.2.0; extra == "doc"
Requires-Dist: sphinx>=7.0; extra == "doc"
Requires-Dist: sphinx-rtd-theme>=1.2; extra == "doc"
Requires-Dist: sphinxcontrib-bibtex>=2.4.0; extra == "doc"
Requires-Dist: sphinx-js>=3.2.2; extra == "doc"
